qoqo_qryd-0.21.0.dist-info/METADATA
qoqo_qryd-0.21.0.dist-info/WHEEL
qoqo_qryd-0.21.0.dist-info/licenses/LICENSE
qoqo_qryd/api_devices.pyi
qoqo_qryd/BSD_LICENSE
qoqo_qryd/DEPENDENCIES
qoqo_qryd/LICENSE_FOR_BINARY_DISTRIBUTION
qoqo_qryd/MIT_LICENSE
qoqo_qryd/OPENSSLLICENSE
qoqo_qryd/pragma_operations.pyi
qoqo_qryd/PYTHON_LICENSE
qoqo_qryd/qoqo_qryd.pyi
qoqo_qryd/qryd_devices.pyi
qoqo_qryd/tweezer_devices.pyi
qoqo_qryd/__init__.py
qoqo_qryd/qoqo_qryd.cp312-win_amd64.pyd
qoqo_qryd-0.21.0.dist-info/RECORD
