Metadata-Version: 2.4
Name: qoqo_qryd
Version: 0.21.0
Requires-Dist: numpy
Requires-Dist: qoqo >=1.16, <1.17
Requires-Dist: qoqo-calculator-pyo3 >=1.2, <1.3
Requires-Dist: tomli ; extra == 'docs'
Requires-Dist: sphinx >=2.1 ; extra == 'docs'
Requires-Dist: nbsphinx ; extra == 'docs'
Requires-Dist: pygments ; extra == 'docs'
Requires-Dist: recommonmark ; extra == 'docs'
Requires-Dist: myst-parser ; extra == 'docs'
Requires-Dist: sphinx-rtd-theme ; extra == 'docs'
Requires-Dist: pillow >=10.3.0 ; extra == 'qollage'
Requires-Dist: ipython >=8.12 ; extra == 'qollage'
Provides-Extra: docs
Provides-Extra: qollage
License-File: LICENSE
Summary: QRyd backend for qoqo quantum computing toolkit
Home-Page: https://github.com/HQSquantumsimulations/qoqo_qryd
Author: HQS Quantum Simulations <info@quantumsimulations.de>
Author-email: HQS Quantum Simulations <info@quantumsimulations.de>
Maintainer-email: HQS Quantum Simulations GmbH <info@quantumsimulations.de>
License: Apache-2.0 AND Apache-2.0 with LLVM-exception AND MIT AND Unicode-DFS-2016 AND
Requires-Python: >=3.8
Project-URL: Source Code, https://github.com/HQSquantumsimulations/qoqo_qryd/
